aars/__init__.py
aars/core.py
aars/exceptions.py
aars/py.typed
aars/utils.py
aars-0.7.5.dist-info/METADATA
aars-0.7.5.dist-info/WHEEL
aars-0.7.5.dist-info/licenses/LICENSE
aars-0.7.5.dist-info/RECORD
