Metadata-Version: 2.1
Name: aars
Version: 0.7.5
Summary: Experimental Object-Document-Mapper using pydantic to store objects on Aleph.im
Project-URL: Homepage, https://github.com/aleph-im/active-record-sdk
Project-URL: Bug Tracker, https://github.com/aleph-im/active-record-sdk/issues
Author-email: Mike Hukiewitz <mike.hukiewitz@robotter.ai>
License-File: LICENSE
Classifier: License :: OSI Approved :: MIT License
Classifier: Operating System :: OS Independent
Classifier: Programming Language :: Python :: 3
Requires-Python: >=3.7
